{
  "district": "静岡1区",
  "candidates": [
    {
      "name": "上川陽子",
      "party": "自民党",
      "step1_ocr_raw_text": "物価高に対処し、地方発の成長を実現\n・物価高対策と安定雇用、持続的な賃金アップ\n・地域・中小企業、スタートアップの活性化\n・観光促進、地域特産品の海外展開\n・半導体、AI（人工知能）、量子、造船等の重点領域への投資\n・海洋、宇宙等のイノベーションと社会実装\n・マンガ、アニメ、模型、茶と食文化：コンテンツで拓く文化大国\n3つの安全保障\n1生活の安全保障：人生100年、つながる“絆”社会\n・国民皆保険・年金制度の堅持、妊娠・出産・子育て支援等\n2食料と水の安全保障：国土保全の再構築\n・危機管理・災害対策の強化 / ・食料自給、供給体制の抜本的強化\n・水・エネルギー、重要資源の保護と確保\n3経済の安全保障\n・世界に必要とされる技術の創出と保護\n・知的財産、人材流出への効果的対策\n・製品、医薬品、重要素材等のサプライチェーン強靭化\n郷土を愛し、地域・世界で活躍する人づくり\n・すべての産業の礎となる人材の育成と確保\n・海洋国家 日本の研究開発、造船、港湾等教育の集積\n・AI社会のデジタル人材、クリエイター育成\n・地域・高等教育機関の整備、奨学金拡充\n新しい日本のかたち\n・「2040年危機」克服へ、日本成長戦略の確実な実現\n・少子高齢化や一極集中による地域格差の是正\n・国民対話による憲法改正",
      "step2_selected_pledges": [
        "半導体、AI、量子、造船等の重点領域への投資を行う",
        "国民皆保険・年金制度を堅持する",
        "食料自給、供給体制を抜本的に強化する",
        "製品、医薬品、重要素材等のサプライチェーンを強靭化する",
        "地域・高等教育機関の整備を行う",
        "奨学金を拡充する",
        "国民対話による憲法改正を実施する"
      ],
      "full_text": "物価高に対処し、地方発の成長を実現\n・物価高対策と安定雇用、持続的な賃金アップ\n・地域・中小企業、スタートアップの活性化\n・観光促進、地域特産品の海外展開\n・半導体、AI（人工知能）、量子、造船等の重点領域への投資\n・海洋、宇宙等のイノベーションと社会実装\n・マンガ、アニメ、模型、茶と食文化：コンテンツで拓く文化大国\n\n3つの安全保障\n1生活の安全保障：人生100年、つながる“絆”社会\n・国民皆保険・年金制度の堅持、妊娠・出産・子育て支援等\n\n2食料と水の安全保障：国土保全の再構築\n・危機管理・災害対策の強化\n・食料自給、供給体制の抜本的強化\n・水・エネルギー、重要資源の保護と確保\n\n3経済の安全保障\n・世界に必要とされる技術の創出と保護\n・知的財産、人材流出への効果的対策\n・製品、医薬品、重要素材等のサプライチェーン強靭化\n\n郷土を愛し、地域・世界で活躍する人づくり\n・すべての産業の礎となる人材の育成と確保\n・海洋国家 日本の研究開発、造船、港湾等教育の集積\n・AI社会のデジタル人材、クリエイター育成\n・地域・高等教育機関の整備、奨学金拡充\n\n新しい日本のかたち\n・「2040年危機」克服へ、日本成長戦略の確実な実現\n・少子高齢化や一極集中による地域格差の是正\n・国民対話による憲法改正"
    }
  ]
}