{
  "district": "東京1区",
  "candidates": [
    {
      "name": "山田みき",
      "party": "自由民主党",
      "manifesto": [
        {
          "title": "都市部における住宅ローン減税の床面積要件の緩和",
          "reason": "「床面積要件」という税制上の具体的なパラメータの変更を明示しており、法改正を通じて客観的に検証可能であるため。",
          "sources": [
            "https://miki-yamada.com/blog/12601.html"
          ],
          "quote_text": "都市部における住宅ローン減税の床面積要件を緩和"
        },
        {
          "title": "土地等の実質的支配者情報の把握と公開",
          "reason": "「把握」「公開」という制度上の具体的なデータ公開義務化を指しており、法制度の変更として客観的検証が可能なため。",
          "sources": [
            "https://miki-yamada.com/blog/12582.html"
          ],
          "quote_text": "国土全域で土地等の実質的支配者情報等を把握し国民に速やかに公開"
        },
        {
          "title": "国民皆歯科健診の法案化",
          "reason": "「法案化」という具体的かつ法的な手続きを通じた制度構築を明示しており、実施の有無が客観的に検証可能なため。",
          "sources": [
            "https://miki-yamada.com/"
          ],
          "quote_text": "国民皆歯科健診の法案化"
        },
        {
          "title": "日本版DBSの導入",
          "reason": "「日本版DBSを導入」という特定の新規制度の設立を断定しており、その制度の存否で客観的に検証可能であるため。",
          "sources": [
            "https://miki-yamada.com/blog/12615.html"
          ],
          "quote_text": "教育・保育・医療等の業務従事者の性犯罪歴を確認する仕組み（日本版DBS）を導入"
        },
        {
          "title": "デジタルリテラシー教育の早期必修化",
          "reason": "「必修化」という教育課程上の具体的な制度変更であり、指導要領の改定等により検証可能であるため。",
          "sources": [
            "https://miki-yamada.com/policy"
          ],
          "quote_text": "デジタルリテラシー教育の早期必修化"
        },
        {
          "title": "憲法改正による自衛隊の明記",
          "reason": "憲法改正という具体的かつ制度的なアクションを明示しており、条文修正の有無によって客観的に達成度が検証可能であるため。",
          "sources": [
            "https://miki-yamada.com/blog/12605.html"
          ],
          "quote_text": "憲法改正による自衛隊の明記"
        },
        {
          "title": "自衛隊員の給与水準改善",
          "reason": "「給与水準」という具体的な報酬体系の変更を指しており、法改正や防衛省の給与規程変更によって検証可能であるため。",
          "sources": [
            "https://miki-yamada.com/blog/12605.html"
          ],
          "quote_text": "自衛隊員の危険な任務に見合った給与水準や居住環境の改善"
        },
        {
          "title": "AI・データサイエンス教育の早期必修化",
          "reason": "「必修化」という教育課程（学習指導要領）における制度のステータス変更を指しており、客観的に検証可能なため。",
          "sources": [
            "https://miki-yamada.com/blog/12591.html"
          ],
          "quote_text": "AIやデータサイエンスに関する教育を早期から必修化"
        }
      ],
      "not-manifesto": [
        {
          "title": "固定資産税・相続税等の見直し・適正化",
          "reason": "いずれも「見直し」や「適正化」といった抽象的な結果を述べているのみで、税率や控除枠をどう変更するかという具体的な制度的手続きや法的アクションが欠如しているため。",
          "sources": [
            "https://miki-yamada.com/policy"
          ],
          "quote_text": "固定資産税・相続税の見直し"
        },
        {
          "title": "地方税制度の構造的見直し",
          "reason": "「見直し」は努力目標に過ぎず、具体的な法改正のアクションや数値目標が欠如しているため。",
          "sources": [
            "https://miki-yamada.com/blog/12601.html"
          ],
          "quote_text": "地方自治体間の財政力格差を是正する地方税制度の構造的見直しを行う。"
        },
        {
          "title": "老朽インフラ・社会資本の維持管理・更新投資の加速",
          "reason": "「加速」という表現は定量的ではなく、実施の有無を客観的に判定できないため。",
          "sources": [
            "https://miki-yamada.com/blog/12601.html"
          ],
          "quote_text": "老朽化するインフラや社会資本の戦略的な維持管理・更新投資を加速させる。"
        },
        {
          "title": "未納防止の仕組みの構築",
          "reason": "「構築」という抽象的なプロセスを述べているに過ぎず、具体的な法改正や税率変更等の変数を含まないため。",
          "sources": [
            "https://miki-yamada.com/blog/12582.html"
          ],
          "quote_text": "未納防止の仕組みを早急に構築します"
        },
        {
          "title": "迷惑行為・特殊詐欺・悪質商法への対策強化",
          "reason": "「厳正な取締り」や「対策の強化」は行政の当然の責務や抽象的な意気込みに過ぎず、具体的な制度導入や法改正を伴わないため。",
          "sources": [
            "https://miki-yamada.com/blog/12615.html"
          ],
          "quote_text": "警察、金融機関、携帯電話事業者などが連携を強化し、電話やインターネット等を用いた組織的な特殊詐欺から国民の財産を守る実効的な対策を強化します。"
        },
        {
          "title": "在留資格制度の見直しと実態把握の強化",
          "reason": "「見直し」「強化」といった抽象的な動詞が含まれており、変更の具体的変数が不明確であるため。",
          "sources": [
            "https://miki-yamada.com/blog/12582.html"
          ],
          "quote_text": "在留資格制度を早急に見直し、制度の間隙を突いた悪用を防ぐとともに、実態把握を強化します"
        },
        {
          "title": "混雑緩和・マナー違反防止に向けた管理と啓発の強化",
          "reason": "「強化」は努力目標であり、具体的な制度変更のパラメーターを特定できていないため。",
          "sources": [
            "https://miki-yamada.com/blog/12582.html"
          ],
          "quote_text": "デジタル技術を活用した予約・入域管理や広報啓発活動を強化します"
        },
        {
          "title": "経済安全保障の強化（インドとの協力・外為法改正）",
          "reason": "「強化」「現状把握」といった抽象的な表現であり、達成手段や具体的な法改正の条文変更内容が示されていないため。",
          "sources": [
            "https://miki-yamada.com/"
          ],
          "quote_text": "インドとの半導体協力、物流の現状把握、経済安全保障の強化。"
        },
        {
          "title": "中小企業支援（融資・価格転嫁・税制）",
          "reason": "「推進」や「支援」という曖昧な表現であり、具体的な法改正や税率等の変更内容が特定されていないため。",
          "sources": [
            "https://miki-yamada.com/"
          ],
          "quote_text": "事業性融資の推進、中小企業支援（価格転嫁、税制優遇、賃上げ支援）。"
        },
        {
          "title": "グリーントランスフォーメーション（GX）の推進",
          "reason": "「推進」は具体的なアクションを示しておらず、定義も抽象的であるため。",
          "sources": [
            "https://miki-yamada.com/blog/12609.html"
          ],
          "quote_text": "循環型経済（サーキュラーエコノミー）の実現、再生可能エネルギーの導入、都市緑化の拡充、断熱住宅の普及など、国・企業・自治体・町内会・個人が連携した一気通貫のGX（グリーントランスフォーメーション）を推進します。"
        },
        {
          "title": "2050年温室効果ガス排出ゼロ",
          "reason": "これは単なる目標設定であり、現時点での具体的な行動方針や法的措置の明示ではないため。",
          "sources": [
            "https://miki-yamada.com/"
          ],
          "quote_text": "2050年温室効果ガス排出ゼロ"
        },
        {
          "title": "働き方改革（長時間労働是正、議員レクのオンライン化）",
          "reason": "「是正」などの抽象的な表現にとどまり、具体的な制度変更内容が不明確であるため。",
          "sources": [
            "https://miki-yamada.com/"
          ],
          "quote_text": "働き方改革（長時間労働是正、議員レクのオンライン化）"
        },
        {
          "title": "社会保障制度（年金・医療・保険）のあり方の検討",
          "reason": "「検討」「見える化」などの表現は手続き的・抽象的であり、具体的な法改正や変数の操作を伴うコミットメントではないため。",
          "sources": [
            "https://miki-yamada.com/blog/12587.html"
          ],
          "quote_text": "保険料と公費負担のバランスを見直すとともに使途を見える化し、全世代が公平に支える持続可能な財源を安定させます。"
        },
        {
          "title": "所得税・法人税のあり方の検討",
          "reason": "「検討」であり、公約としての具体的な法改正案ではないため。",
          "sources": [
            "https://miki-yamada.com/"
          ],
          "quote_text": "所得税・法人税のあり方の検討"
        },
        {
          "title": "自衛官の処遇改善",
          "reason": "「改善」が何を指すのか不明（給与なのか、手当なのか等）であり、検証不能であるため。",
          "sources": [
            "https://miki-yamada.com/"
          ],
          "quote_text": "自衛官の処遇改善"
        },
        {
          "title": "防衛予算・装備・体制の強化",
          "reason": "「拡充」「強化」の基準が曖昧であり、具体的な数値目標や法的要件の変更が示されていないため。",
          "sources": [
            "https://miki-yamada.com/blog/12605.html"
          ],
          "quote_text": "防衛力の抜本的な強化に必要な財源を確保し"
        },
        {
          "title": "離婚後の子の養育のあり方の検討",
          "reason": "「検討」という表現は手続き的であり、公約ではないため。",
          "sources": [
            "https://miki-yamada.com/"
          ],
          "quote_text": "父母の離婚後の子の養育のあり方の検討"
        },
        {
          "title": "街区レベルでの緑化と再生可能エネルギー導入の加速",
          "reason": "「促進」「加速」といった意欲表現であり、具体的な制度変更内容や法的な数値基準が不明であるため。",
          "sources": [
            "https://miki-yamada.com/blog/12609.html"
          ],
          "quote_text": "都市のヒートアイランド現象対策として、街区レベルでの緑化を促進するとともに、再生可能エネルギーの最大限の導入を加速します。"
        },
        {
          "title": "地域主体の脱炭素化を促す支援枠組みの構築",
          "reason": "「枠組みを構築」という表現は抽象的であり、客観的に検証可能な具体的制度変更内容ではないため。",
          "sources": [
            "https://miki-yamada.com/blog/12609.html"
          ],
          "quote_text": "国・企業・自治体・個人が連携した地域主体の脱炭素化を促すため、地域の再生可能エネルギー導入や省エネを支援する枠組みを構築します。"
        },
        {
          "title": "住宅・建築物の省エネ化徹底と省エネ基準適合義務化の着実な実施",
          "reason": "「徹底」「着実に実施」は既存制度の運用の再確認であり、新たな政治的アクションではないため。",
          "sources": [
            "https://miki-yamada.com/blog/12609.html"
          ],
          "quote_text": "住宅・建築物の省エネ化を徹底するため、高効率な給湯器や断熱窓などの導入を支援し、省エネ基準適合義務化を着実に実施します。"
        },
        {
          "title": "地域の防災・減災対策と連携したインフラの強靭化",
          "reason": "「進める」「加速」という抽象的な意欲表現であり、具体的なアクションが不明瞭であるため。",
          "sources": [
            "https://miki-yamada.com/blog/12609.html"
          ],
          "quote_text": "気候変動と防災への複合的な対応として、地域の防災・減災対策と連携したインフラの強靭化を進め、安全な地域づくりを加速します。"
        },
        {
          "title": "防犯活動および地域見守り体制の強化",
          "reason": "「支援を拡充」「体制を強化」といった曖昧な表現であり、具体的な予算額や制度上の法的要件の変更を伴わないため。",
          "sources": [
            "https://miki-yamada.com/blog/12615.html"
          ],
          "quote_text": "地域の自主的な防犯活動を促進するため、防犯カメラの設置や通学路の安全確保等に対する支援を拡充できるよう自治体を支援し、地域の見守り体制を強化します。"
        },
        {
          "title": "性犯罪から子供を守る環境整備",
          "reason": "「環境を整備」という抽象的な表現であり、具体的な法改正や制度設計を指していないため。",
          "sources": [
            "https://miki-yamada.com/blog/12615.html"
          ],
          "quote_text": "性犯罪から子どもを守るための環境を整備します"
        },
        {
          "title": "ストーカー・DV犯罪防止と警察体制の強化",
          "reason": "「対応を強化」「体制を強化」という表現は具体的なアクションではなく努力目標の範疇であるため。",
          "sources": [
            "https://miki-yamada.com/blog/12615.html"
          ],
          "quote_text": "ストーカー・DV等の悪質な事案や犯罪の未然防止に向け、SNSを利用した事案への対応や危険人物への対応を強化するための警察の体制を強化します。"
        },
        {
          "title": "物価高への対応",
          "reason": "抽象的な目標であり、何を具体的にどうするかが不明で、検証可能なアクションではないため。",
          "sources": [
            "https://miki-yamada.com/policy"
          ],
          "quote_text": "物価高への対応"
        },
        {
          "title": "予防医療の公的支援拡充",
          "reason": "「拡充」は恣意的な表現であり、何をもって達成とみなすかの客観的指標がないため。",
          "sources": [
            "https://miki-yamada.com/policy"
          ],
          "quote_text": "予防医療の公的支援拡充"
        },
        {
          "title": "診療報酬体系の適正化",
          "reason": "「適正化」が何を指すのか不明瞭であり、変数が固定されていないため。",
          "sources": [
            "https://miki-yamada.com/policy"
          ],
          "quote_text": "診療報酬体系の適正化"
        },
        {
          "title": "住宅ローン減税の拡充",
          "reason": "「拡充」の定義が不明確であり、控除率や控除期間など、変更する変数が具体的に示されていないため。",
          "sources": [
            "https://miki-yamada.com/policy"
          ],
          "quote_text": "住宅ローン減税の拡充"
        },
        {
          "title": "行政改革・人事制度改革",
          "reason": "「改革」「強化」「導入」という表現は抽象的であり、具体的な法制度や評価基準が不明で検証不可能であるため。",
          "sources": [
            "https://miki-yamada.com/blog/12595.html"
          ],
          "quote_text": "政官民一体の行政改革 政治、行政、民間の人材が互いに混ざり合い、多様な人材がその能力を最大限に活かし活躍できる社会を実現します。"
        },
        {
          "title": "医療・介護・福祉従事者の処遇改善",
          "reason": "「改善」「仕組み」という抽象的な対象に対する意欲表明であり、具体的な制度変更の変数が特定されていないため。",
          "sources": [
            "https://miki-yamada.com/blog/12587.html"
          ],
          "quote_text": "医療関係者や介護・看護・障害福祉サービス従事者の処遇改善を不断に行い、現場の努力が正当に評価され、賃上げを継続できる仕組みと安定財源を確保します。"
        },
        {
          "title": "児童手当の抜本的拡充と高等教育授業料の対象拡大",
          "reason": "「抜本的拡充」「対象拡大」は具体的な数値や法改正内容を欠いており、客観的な達成判定が不可能なため。",
          "sources": [
            "https://miki-yamada.com/blog/12587.html"
          ],
          "quote_text": "少子化対策として、児童手当の抜本的拡充や高等教育の授業料等減免の対象拡大を行い、結婚・妊娠・出産・子育てにわたる切れ目のない経済的支援を充実させます。"
        },
        {
          "title": "生活必需品（燃料・エネルギー）の価格支援",
          "reason": "「機動的に実施」は抽象的であり、具体的にどの数値や制度を変更するかが明記されていないため。",
          "sources": [
            "https://miki-yamada.com/blog/12572.html"
          ],
          "quote_text": "燃料油価格の定額引下げや電気・ガス料金支援など、生活必需品の価格安定化を機動的に実施する。"
        },
        {
          "title": "所得税減税等の検討",
          "reason": "「見直しを検討」「支援する」という手続き的・意欲的表現であり、断定的なコミットメントではないため。",
          "sources": [
            "https://miki-yamada.com/blog/12572.html"
          ],
          "quote_text": "物価上昇に合わせた基礎控除等の見直しを検討し、所得税減税や低所得者給付を通じて、家計の可処分所得向上を支援する。"
        },
        {
          "title": "価格転嫁ガイドラインの法的拘束力強化および下請法執行",
          "reason": "「強化」「厳正に執行する」は努力目標や当然の責務であり、具体的な法改正等のアクションとして定義されていないため。",
          "sources": [
            "https://miki-yamada.com/blog/12572.html"
          ],
          "quote_text": "価格転嫁ガイドラインの法的拘束力を強化し、下請Gメンや公正取引委員会の人材・執行体制を拡充した上で「中小受託取引適正化法（改正下請法）」を厳正に執行する。"
        },
        {
          "title": "賃上げ支援の強化",
          "reason": "「抜本的に強化」「後押しする」といった抽象的な表現であり、達成度が客観的に測定できないため。",
          "sources": [
            "https://miki-yamada.com/blog/12572.html"
          ],
          "quote_text": "賃上げ企業への税制・補助金支援を抜本的に強化し、福祉分野を含む全産業の労務費転嫁と処遇改善を後押しする。"
        },
        {
          "title": "中小企業の生産性向上支援",
          "reason": "「充実させる」という表現は抽象的であり、どのような制度変更を指すのかが不明確であるため。",
          "sources": [
            "https://miki-yamada.com/blog/12572.html"
          ],
          "quote_text": "中小企業の生産性向上を支援するため、人手不足対応・デジタル化・設備投資を支援する補助金を充実させる。"
        },
        {
          "title": "防衛装備品の調達迅速化",
          "reason": "「迅速化」という目標はプロセス上の努力目標であり、客観的な完了基準が存在しないため。",
          "sources": [
            "https://miki-yamada.com/blog/12605.html"
          ],
          "quote_text": "防衛装備品の調達を迅速化するとともに"
        },
        {
          "title": "海上保安庁の機能強化",
          "reason": "「機能強化」という曖昧な表現であり、具体的な法改正や予算措置としての変数が特定されていないため。",
          "sources": [
            "https://miki-yamada.com/blog/12605.html"
          ],
          "quote_text": "海上保安庁等関係機関の機能を強化"
        },
        {
          "title": "自由で開かれたインド太平洋（FOIP）の推進",
          "reason": "外交方針という抽象的なスローガンであり、具体的な政策手段や法的なコミットメントが欠如しているため。",
          "sources": [
            "https://miki-yamada.com/blog/12605.html"
          ],
          "quote_text": "自由で開かれたインド太平洋を推進します"
        },
        {
          "title": "多国間の安全保障協力の強化",
          "reason": "「協力の強化」という外交上の表現は具体的な制度的アクションを伴わず、検証不可能なため。",
          "sources": [
            "https://miki-yamada.com/blog/12605.html"
          ],
          "quote_text": "日米同盟を中核とする多国間の安全保障協力を強化"
        },
        {
          "title": "非化石エネルギー導入・開発及びサプライチェーン構築の推進",
          "reason": "「推進」という表現が含まれ、具体的な制度的変更や数値的コミットメントを伴わないため。",
          "sources": [
            "https://miki-yamada.com/blog/12618.html"
          ],
          "quote_text": "合成燃料、水素・アンモニア等の非化石エネルギー導入・開発及びサプライチェーン構築を強力に推進し、資源自立型のエネルギー需給構造へ転換します。"
        },
        {
          "title": "循環型経済の実現とモノづくりの振興",
          "reason": "「振興を図る」「実現する」といった曖昧な意気込みであり、観測可能な具体的アクションが含まれていないため。",
          "sources": [
            "https://miki-yamada.com/blog/12618.html"
          ],
          "quote_text": "技術開発支援やサプライチェーン構築を通じて、使用済み製品の回収・リサイクルが円滑に進むようなモノづくりの振興を図り、循環型経済を実現します。"
        },
        {
          "title": "エネルギー分野における規制改革の推進",
          "reason": "「推進」という表現が含まれており、改革の具体的な内容や変数が定義されていないため。",
          "sources": [
            "https://miki-yamada.com/blog/12618.html"
          ],
          "quote_text": "エネルギー分野における新規技術導入やデジタル技術やAI等の社会実装を加速する規制改革を強力に推進します。"
        },
        {
          "title": "成長分野における人材投資・学び直しの強化",
          "reason": "「強化」「整備」「促進」という努力目標であり、客観的に達成を判定できる変数や制度変更がないため。",
          "sources": [
            "https://miki-yamada.com/blog/12618.html"
          ],
          "quote_text": "環境・エネルギー及びデジタル・AI等の成長分野における人材投資や学び直しを強化するとともに、優秀な日本人が世界で活躍できる環境を整備し、国際的な頭脳循環を促進します。"
        },
        {
          "title": "カーボンプライシングを活用した経済成長",
          "reason": "「活用」や「両立」という抽象的なスローガンであり、具体的な政策手段や法改正のアクションが示されていないため。",
          "sources": [
            "https://miki-yamada.com/blog/12618.html"
          ],
          "quote_text": "カーボンプライシングを始めとした環境分野の市場機能を活用し、脱炭素化と経済成長を両立させます。"
        },
        {
          "title": "教育（英語・歴史・探究型学習）の推進",
          "reason": "「推進」「徹底」「枠組み構築」という努力目標であり、具体的な制度変更や変数の操作が明示されていないため。",
          "sources": [
            "https://miki-yamada.com/blog/12591.html"
          ],
          "quote_text": "学校・教職員の指導体制を強化し、教師の専門性を高める研修の強化や、ビジネス人材等多様な人材の参画を促進します"
        }
      ]
    }
  ]
}